Metadata-Version: 2.1
Name: autora-experimentalist-nearest-value
Version: 2.2.0
Summary: A experimentalist which returns the nearest values between the input samples and the allowed values, without replacement.
Author-email: "Built by Sebastian Musslick, restructured by Chad Williams" <sebastian_musslick@brown.edu>
License: MIT License
Project-URL: homepage, http://www.empiricalresearch.ai
Project-URL: repository, https://github.com/AutoResearch/autora-experimentalist-nearest-value
Project-URL: documentation, https://autoresearch.github.io/autora/
Requires-Python: <4,>=3.8
License-File: LICENSE
Requires-Dist: autora-core >=3.1.0
Requires-Dist: scikit-learn
Provides-Extra: dev
Requires-Dist: autora-core[dev] ; extra == 'dev'
